pornhub_generate_playlist-0.1.0.dist-info/METADATA
pornhub_generate_playlist-0.1.0.dist-info/WHEEL
pornhub_generate_playlist-0.1.0.dist-info/entry_points.txt
pornhub_generate_playlist/__init__.py
pornhub_generate_playlist/lib/__init__.py
pornhub_generate_playlist/lib/clipboard_handler.py
pornhub_generate_playlist/lib/haruna_handler.py
pornhub_generate_playlist/lib/m3u8_handler.py
pornhub_generate_playlist/pornhub_generate_playlist.py
pornhub_generate_playlist-0.1.0.dist-info/RECORD
